{
  "ParticipantID": "920fb7a7-1b23-4ccd-8a68-76cb7df66ee6",
  "startTimeStamp": "2023-06-27T15:46:28+01:00",
  "endTimeStamp": "2023-06-27T15:58:51+01:00",
  "tasks": [
    {
      "sourcePosition": [
        1.27668822,
        -0.0514381267,
        -2.40970278
      ],
      "selectedSource": [
        2.643388,
        0.0602400042,
        -0.0288487077
      ],
      "listenerPosition": [
        2.603232,
        0.0247987136,
        -0.5553809
      ],
      "timeStamp": "2023-06-27T15:47:47+01:00",
      "clip_name": "auralisation_Cube (6)_drums",
      "rt": true
    },
    {
      "sourcePosition": [
        -2.81436348,
        -0.0514381267,
        -0.0343455672
      ],
      "selectedSource": [
        -1.357251,
        0.0602400042,
        -2.36096478
      ],
      "listenerPosition": [
        -0.870395,
        0.0434295945,
        -2.40242124
      ],
      "timeStamp": "2023-06-27T15:48:03+01:00",
      "clip_name": "arp",
      "rt": false
    },
    {
      "sourcePosition": [
        1.3285718,
        -0.0514381267,
        2.39032269
      ],
      "selectedSource": [
        1.24445093,
        0.0602400042,
        -2.36096478
      ],
      "listenerPosition": [
        0.669071555,
        0.04327631,
        -2.29279017
      ],
      "timeStamp": "2023-06-27T15:48:13+01:00",
      "clip_name": "auralisation_Cube (4)_arp",
      "rt": true
    },
    {
      "sourcePosition": [
        1.3285718,
        -0.0514381267,
        2.39032269
      ],
      "selectedSource": [
        -1.41615987,
        0.0602400042,
        2.337607
      ],
      "listenerPosition": [
        -1.90167189,
        0.0455473475,
        2.29355574
      ],
      "timeStamp": "2023-06-27T15:48:41+01:00",
      "clip_name": "arp",
      "rt": false
    },
    {
      "sourcePosition": [
        1.27668822,
        -0.0514381267,
        -2.40970278
      ],
      "selectedSource": [
        1.24445093,
        0.0602400042,
        -2.36096478
      ],
      "listenerPosition": [
        0.8942792,
        0.0407943241,
        -2.00881672
      ],
      "timeStamp": "2023-06-27T15:49:10+01:00",
      "clip_name": "drums",
      "rt": false
    },
    {
      "sourcePosition": [
        -1.38113356,
        -0.0514381267,
        -2.41429615
      ],
      "selectedSource": [
        -1.357251,
        0.0602400042,
        -2.36096478
      ],
      "listenerPosition": [
        -0.902094841,
        0.0346441381,
        -1.94740129
      ],
      "timeStamp": "2023-06-27T15:51:05+01:00",
      "clip_name": "arp",
      "rt": false
    },
    {
      "sourcePosition": [
        1.27668822,
        -0.0514381267,
        -2.40970278
      ],
      "selectedSource": [
        1.24445093,
        0.0602400042,
        -2.36096478
      ],
      "listenerPosition": [
        0.8552084,
        0.0453545637,
        -1.85414886
      ],
      "timeStamp": "2023-06-27T15:51:35+01:00",
      "clip_name": "auralisation_Cube (6)_arp",
      "rt": true
    },
    {
      "sourcePosition": [
        1.3285718,
        -0.0514381267,
        2.39032269
      ],
      "selectedSource": [
        1.30335975,
        0.0602400042,
        2.337607
      ],
      "listenerPosition": [
        1.00762475,
        0.0550500043,
        1.94536936
      ],
      "timeStamp": "2023-06-27T15:52:17+01:00",
      "clip_name": "auralisation_Cube (4)_singing",
      "rt": true
    },
    {
      "sourcePosition": [
        -1.449609,
        -0.0514381267,
        2.385521
      ],
      "selectedSource": [
        -1.41615987,
        0.0602400042,
        2.337607
      ],
      "listenerPosition": [
        -0.969416738,
        0.0534072146,
        2.04320765
      ],
      "timeStamp": "2023-06-27T15:52:40+01:00",
      "clip_name": "arp",
      "rt": false
    },
    {
      "sourcePosition": [
        2.70168328,
        -0.0514381267,
        -0.0248120427
      ],
      "selectedSource": [
        1.24445093,
        0.0602400042,
        -2.36096478
      ],
      "listenerPosition": [
        0.882160068,
        0.0432913937,
        -1.92924416
      ],
      "timeStamp": "2023-06-27T15:52:57+01:00",
      "clip_name": "auralisation_Cube (5)_singing",
      "rt": true
    },
    {
      "sourcePosition": [
        1.3285718,
        -0.0514381267,
        2.39032269
      ],
      "selectedSource": [
        1.30335975,
        0.0602400042,
        2.337607
      ],
      "listenerPosition": [
        1.01540983,
        0.0519778132,
        1.85989022
      ],
      "timeStamp": "2023-06-27T15:53:10+01:00",
      "clip_name": "auralisation_Cube (4)_drums",
      "rt": true
    },
    {
      "sourcePosition": [
        2.70168328,
        -0.0514381267,
        -0.0248120427
      ],
      "selectedSource": [
        2.643388,
        0.0602400042,
        -0.0288487077
      ],
      "listenerPosition": [
        2.572045,
        0.0477610119,
        -0.537278652
      ],
      "timeStamp": "2023-06-27T15:53:33+01:00",
      "clip_name": "drums",
      "rt": false
    },
    {
      "sourcePosition": [
        1.27668822,
        -0.0514381267,
        -2.40970278
      ],
      "selectedSource": [
        1.24445093,
        0.0602400042,
        -2.36096478
      ],
      "listenerPosition": [
        0.6830363,
        0.04434102,
        -2.52036667
      ],
      "timeStamp": "2023-06-27T15:53:44+01:00",
      "clip_name": "arp",
      "rt": false
    },
    {
      "sourcePosition": [
        -2.81436348,
        -0.0514381267,
        -0.0343455672
      ],
      "selectedSource": [
        -2.75618768,
        0.0602400042,
        -0.0288487077
      ],
      "listenerPosition": [
        -3.141561,
        0.0519348234,
        -0.5235485
      ],
      "timeStamp": "2023-06-27T15:54:01+01:00",
      "clip_name": "drums",
      "rt": false
    },
    {
      "sourcePosition": [
        -1.38113356,
        -0.0514381267,
        -2.41429615
      ],
      "selectedSource": [
        -1.357251,
        0.0602400042,
        -2.36096478
      ],
      "listenerPosition": [
        -1.61644256,
        0.03807826,
        -2.52302933
      ],
      "timeStamp": "2023-06-27T15:54:10+01:00",
      "clip_name": "drums",
      "rt": false
    },
    {
      "sourcePosition": [
        2.70168328,
        -0.0514381267,
        -0.0248120427
      ],
      "selectedSource": [
        2.643388,
        0.0602400042,
        -0.0288487077
      ],
      "listenerPosition": [
        2.61598182,
        0.0473138765,
        -0.594675958
      ],
      "timeStamp": "2023-06-27T15:54:40+01:00",
      "clip_name": "arp",
      "rt": false
    },
    {
      "sourcePosition": [
        -1.38113356,
        -0.0514381267,
        -2.41429615
      ],
      "selectedSource": [
        -1.357251,
        0.0602400042,
        -2.36096478
      ],
      "listenerPosition": [
        -1.102376,
        0.0409046523,
        -2.160237
      ],
      "timeStamp": "2023-06-27T15:55:08+01:00",
      "clip_name": "singing",
      "rt": false
    },
    {
      "sourcePosition": [
        1.27668822,
        -0.0514381267,
        -2.40970278
      ],
      "selectedSource": [
        1.24445093,
        0.0602400042,
        -2.36096478
      ],
      "listenerPosition": [
        0.9125375,
        0.04508283,
        -2.02116036
      ],
      "timeStamp": "2023-06-27T15:55:23+01:00",
      "clip_name": "singing",
      "rt": false
    },
    {
      "sourcePosition": [
        2.70168328,
        -0.0514381267,
        -0.0248120427
      ],
      "selectedSource": [
        2.643388,
        0.0602400042,
        -0.0288487077
      ],
      "listenerPosition": [
        2.629697,
        0.0426168,
        -0.48515743
      ],
      "timeStamp": "2023-06-27T15:55:46+01:00",
      "clip_name": "auralisation_Cube (5)_arp",
      "rt": true
    },
    {
      "sourcePosition": [
        -1.449609,
        -0.0514381267,
        2.385521
      ],
      "selectedSource": [
        -1.41615987,
        0.0602400042,
        2.337607
      ],
      "listenerPosition": [
        -1.037772,
        0.0548130758,
        1.91684937
      ],
      "timeStamp": "2023-06-27T15:56:09+01:00",
      "clip_name": "drums",
      "rt": false
    },
    {
      "sourcePosition": [
        1.27668822,
        -0.0514381267,
        -2.40970278
      ],
      "selectedSource": [
        1.24445093,
        0.0602400042,
        -2.36096478
      ],
      "listenerPosition": [
        0.8961999,
        0.0435664281,
        -1.97809768
      ],
      "timeStamp": "2023-06-27T15:56:25+01:00",
      "clip_name": "auralisation_Cube (6)_singing",
      "rt": true
    },
    {
      "sourcePosition": [
        2.70168328,
        -0.0514381267,
        -0.0248120427
      ],
      "selectedSource": [
        2.643388,
        0.0602400042,
        -0.0288487077
      ],
      "listenerPosition": [
        2.59560919,
        0.0470795,
        -0.562072158
      ],
      "timeStamp": "2023-06-27T15:56:46+01:00",
      "clip_name": "singing",
      "rt": false
    },
    {
      "sourcePosition": [
        -1.449609,
        -0.0514381267,
        2.385521
      ],
      "selectedSource": [
        -1.41615987,
        0.0602400042,
        2.337607
      ],
      "listenerPosition": [
        -1.0119859,
        0.0472187027,
        2.00202
      ],
      "timeStamp": "2023-06-27T15:57:10+01:00",
      "clip_name": "singing",
      "rt": false
    },
    {
      "sourcePosition": [
        2.70168328,
        -0.0514381267,
        -0.0248120427
      ],
      "selectedSource": [
        2.643388,
        0.0602400042,
        -0.0288487077
      ],
      "listenerPosition": [
        2.53544521,
        0.04625592,
        -0.584359765
      ],
      "timeStamp": "2023-06-27T15:57:37+01:00",
      "clip_name": "auralisation_Cube (5)_drums",
      "rt": true
    },
    {
      "sourcePosition": [
        1.3285718,
        -0.0514381267,
        2.39032269
      ],
      "selectedSource": [
        1.30335975,
        0.0602400042,
        2.337607
      ],
      "listenerPosition": [
        0.9635585,
        0.042915538,
        1.96272993
      ],
      "timeStamp": "2023-06-27T15:58:02+01:00",
      "clip_name": "drums",
      "rt": false
    },
    {
      "sourcePosition": [
        -2.81436348,
        -0.0514381267,
        -0.0343455672
      ],
      "selectedSource": [
        -2.75618768,
        0.0602400042,
        -0.0288487077
      ],
      "listenerPosition": [
        -2.981095,
        0.04786521,
        -0.411252439
      ],
      "timeStamp": "2023-06-27T15:58:24+01:00",
      "clip_name": "singing",
      "rt": false
    },
    {
      "sourcePosition": [
        1.3285718,
        -0.0514381267,
        2.39032269
      ],
      "selectedSource": [
        1.30335975,
        0.0602400042,
        2.337607
      ],
      "listenerPosition": [
        1.077354,
        0.0450931266,
        1.884829
      ],
      "timeStamp": "2023-06-27T15:58:49+01:00",
      "clip_name": "singing",
      "rt": false
    }
  ]
}